EtlOrcPos/__init__.py
EtlOrcPos-0.0.1.dist-info/LICENSE.txt
EtlOrcPos-0.0.1.dist-info/METADATA
EtlOrcPos-0.0.1.dist-info/WHEEL
EtlOrcPos-0.0.1.dist-info/top_level.txt
EtlOrcPos-0.0.1.dist-info/RECORD
