Metadata-Version: 2.1
Name: EtlOrcPos
Version: 0.0.1
Summary: ETL Orale to Postgresql
Home-page: https://github.com/rohitjangirdata/EtlOrcPos.git
Author: Rohit jangir
Author-email: rohit.jangir.data@gmail.com
License: UNKNOWN
Platform: UNKNOWN
Classifier: Programming Language :: Python :: 3
Classifier: License :: OSI Approved :: MIT License
Classifier: Operating System :: OS Independent
